bytedocs_flask/__init__.py
bytedocs_flask/ai/__init__.py
bytedocs_flask/ai/context_optimizer.py
bytedocs_flask/ai/factory.py
bytedocs_flask/ai/types.py
bytedocs_flask/ai/providers/__init__.py
bytedocs_flask/ai/providers/anthropic_client.py
bytedocs_flask/ai/providers/gemini_client.py
bytedocs_flask/ai/providers/openai_client.py
bytedocs_flask/ai/providers/openrouter_client.py
bytedocs_flask/auth/__init__.py
bytedocs_flask/core/__init__.py
bytedocs_flask/core/bytedocs.py
bytedocs_flask/core/config.py
bytedocs_flask/core/types.py
bytedocs_flask/parser/__init__.py
bytedocs_flask/parser/ast_analyzer.py
bytedocs_flask/parser/route_analyzer.py
bytedocs_flask/ui/__init__.py
bytedocs_flask/ui/handlers.py
bytedocs_flask/ui/template_loader.py
bytedocs_flask/ui/templates/template.html
bytedocs_flask-1.0.1.dist-info/licenses/LICENSE
bytedocs_flask-1.0.1.dist-info/METADATA
bytedocs_flask-1.0.1.dist-info/WHEEL
bytedocs_flask-1.0.1.dist-info/top_level.txt
bytedocs_flask-1.0.1.dist-info/RECORD
