Metadata-Version: 2.4
Name: bytedocs-flask
Version: 1.0.1
Summary: Alternative to Swagger with better design, auto-detection, and AI integration
Home-page: https://github.com/aibnuhibban/bytedocs-flask
Author: ByteDocs Contributors
Author-email: 
License-Expression: MIT
Project-URL: Homepage, https://github.com/aibnuhibban/bytedocs-flask
Project-URL: Bug Reports, https://github.com/aibnuhibban/bytedocs-flask/issues
Project-URL: Source, https://github.com/aibnuhibban/bytedocs-flask
Keywords: flask,documentation,api,swagger,openapi,bytedocs,auto-documentation,api-doc,rest-api,python
Classifier: Development Status :: 4 - Beta
Classifier: Intended Audience :: Developers
Classifier: Programming Language :: Python :: 3
Classifier: Programming Language :: Python :: 3.8
Classifier: Programming Language :: Python :: 3.9
Classifier: Programming Language :: Python :: 3.10
Classifier: Programming Language :: Python :: 3.11
Classifier: Programming Language :: Python :: 3.12
Classifier: Framework :: Flask
Classifier: Topic :: Documentation
Classifier: Topic :: Software Development :: Documentation
Requires-Python: >=3.8
License-File: LICENSE
Requires-Dist: flask>=2.0.0
Requires-Dist: pyyaml>=6.0
Requires-Dist: python-dotenv>=1.0.0
Provides-Extra: ai
Requires-Dist: openai>=2.0.0; extra == "ai"
Requires-Dist: google-generativeai>=0.8.0; extra == "ai"
Requires-Dist: anthropic>=0.70.0; extra == "ai"
Provides-Extra: all
Requires-Dist: openai>=2.0.0; extra == "all"
Requires-Dist: google-generativeai>=0.8.0; extra == "all"
Requires-Dist: anthropic>=0.70.0; extra == "all"
Provides-Extra: dev
Requires-Dist: pytest>=7.0.0; extra == "dev"
Requires-Dist: build>=1.0.0; extra == "dev"
Requires-Dist: twine>=4.0.0; extra == "dev"
Dynamic: home-page
Dynamic: license-file
Dynamic: requires-python
